whisperer/__init__.py
whisperer/admin.py
whisperer/apps.py
whisperer/client.py
whisperer/codes.py
whisperer/conf.py
whisperer/countdown.py
whisperer/events.py
whisperer/exceptions.py
whisperer/models.py
whisperer/services.py
whisperer/tasks.py
whisperer/urls.py
whisperer/utils.py
whisperer/validators.py
whisperer/migrations/0001_initial.py
whisperer/migrations/0002_webhook_additional_headers.py
whisperer/migrations/0003_auto_20200505_0853.py
whisperer/migrations/0004_webhook_retry_count.py
whisperer/migrations/0005_webhook_config.py
whisperer/migrations/0006_auto_20200925_1710.py
whisperer/migrations/0007_event_queue.py
whisperer/migrations/0008_ayto_20240323_2301.py
whisperer/migrations/0009_ayto_20250108_0635.py
whisperer/migrations/0010_webhookevent_response_time.py
whisperer/migrations/__init__.py
whisperer/resources/__init__.py
whisperer/resources/filters.py
whisperer/resources/serializers.py
whisperer/resources/views.py
dj_whisperer-0.5.1.dist-info/LICENSE.txt
dj_whisperer-0.5.1.dist-info/METADATA
dj_whisperer-0.5.1.dist-info/WHEEL
dj_whisperer-0.5.1.dist-info/top_level.txt
dj_whisperer-0.5.1.dist-info/RECORD
